{
  "CellEditingDemo.tsx": {
    "id": "x8pcm3",
    "url": "https://codesandbox.io/s/x8pcm3"
  },
  "CellHighlightingDemo.tsx": {
    "id": "8y2mxt",
    "url": "https://codesandbox.io/s/8y2mxt"
  },
  "CellRendererDemo.tsx": {
    "id": "frmqhf",
    "url": "https://codesandbox.io/s/frmqhf"
  },
  "ColumnAlignmentDemo.tsx": {
    "id": "kh73pj",
    "url": "https://codesandbox.io/s/kh73pj"
  },
  "ColumnPinningDemo.tsx": {
    "id": "zw8wc6",
    "url": "https://codesandbox.io/s/zw8wc6"
  },
  "ColumnReorderingDemo.tsx": {
    "id": "dv54wk",
    "url": "https://codesandbox.io/s/dv54wk"
  },
  "ColumnResizingDemo.tsx": {
    "id": "rn9z48",
    "url": "https://codesandbox.io/s/rn9z48"
  },
  "ColumnSortingDemo.tsx": {
    "id": "ydkrr6",
    "url": "https://codesandbox.io/s/ydkrr6"
  },
  "ColumnVisibilityDemo.tsx": {
    "id": "x4zwyv",
    "url": "https://codesandbox.io/s/x4zwyv"
  },
  "CustomIconsDemo.tsx": {
    "id": "dyp25d",
    "url": "https://codesandbox.io/s/dyp25d"
  },
  "CustomRenderersDemo.tsx": {
    "id": "k2xcds",
    "url": "https://codesandbox.io/s/k2xcds"
  },
  "LiveUpdateDemo.tsx": {
    "id": "ztj3yt",
    "url": "https://codesandbox.io/s/ztj3yt"
  },
  "NestedHeadersDemo.tsx": {
    "id": "rx7sjd",
    "url": "https://codesandbox.io/s/rx7sjd"
  },
  "PaginationDemo.tsx": {
    "id": "ghzqym",
    "url": "https://codesandbox.io/s/ghzqym"
  },
  "QuickStartDemo.tsx": {
    "id": "rmkyrw",
    "url": "https://codesandbox.io/s/rmkyrw"
  },
  "RowGroupingDemo.tsx": {
    "id": "xmcy4d",
    "url": "https://codesandbox.io/s/xmcy4d"
  },
  "RowHeightDemo.tsx": {
    "id": "jjqj4x",
    "url": "https://codesandbox.io/s/jjqj4x"
  },
  "ThemesDemo.tsx": {
    "id": "mvf5zr",
    "url": "https://codesandbox.io/s/mvf5zr"
  },
  "src/CustomThemeDemo.tsx": {
    "id": "sj5m2f",
    "url": "https://codesandbox.io/s/sj5m2f"
  },
  "examples/billing/BillingExample.tsx": {
    "id": "hwhp28",
    "url": "https://codesandbox.io/s/hwhp28"
  },
  "examples/hr/HRExample.tsx": {
    "id": "22k55w",
    "url": "https://codesandbox.io/s/22k55w"
  },
  "examples/manufacturing/ManufacturingExample.tsx": {
    "id": "7r722h",
    "url": "https://codesandbox.io/s/7r722h"
  },
  "examples/sales/SalesExample.tsx": {
    "id": "dk3mdr",
    "url": "https://codesandbox.io/s/dk3mdr"
  },
  "examples/finance/FinanceExample.tsx": {
    "id": "739tqz",
    "url": "https://codesandbox.io/s/739tqz"
  },
  "ColumnFilteringDemo.tsx": {
    "id": "ld28z3",
    "url": "https://codesandbox.io/s/ld28z3"
  }
}