{
  "ProgrammaticControlDemo.tsx": {
    "id": "8725sl",
    "url": "https://codesandbox.io/s/8725sl"
  },
  "examples/spreadsheet/SpreadsheetExample.tsx": {
    "id": "xs94n9",
    "url": "https://codesandbox.io/s/xs94n9"
  },
  "AggregateFunctionsDemo.tsx": {
    "id": "p64r7l",
    "url": "https://codesandbox.io/s/p64r7l"
  },
  "CSVExportDemo.tsx": {
    "id": "v25kkw",
    "url": "https://codesandbox.io/s/v25kkw"
  },
  "CellClickingDemo.tsx": {
    "id": "v6s6nc",
    "url": "https://codesandbox.io/s/v6s6nc"
  },
  "CellEditingDemo.tsx": {
    "id": "6qz8yq",
    "url": "https://codesandbox.io/s/6qz8yq"
  },
  "CellHighlightingDemo.tsx": {
    "id": "9szj3z",
    "url": "https://codesandbox.io/s/9szj3z"
  },
  "CellRendererDemo.tsx": {
    "id": "4q2p3s",
    "url": "https://codesandbox.io/s/4q2p3s"
  },
  "ChartsDemo.tsx": {
    "id": "pqgjwl",
    "url": "https://codesandbox.io/s/pqgjwl"
  },
  "CollapsibleColumnsDemo.tsx": {
    "id": "g3jr69",
    "url": "https://codesandbox.io/s/g3jr69"
  },
  "ColumnAlignmentDemo.tsx": {
    "id": "kzfcn7",
    "url": "https://codesandbox.io/s/kzfcn7"
  },
  "ColumnEditingDemo.tsx": {
    "id": "4cr3tm",
    "url": "https://codesandbox.io/s/4cr3tm"
  },
  "ColumnFilteringDemo.tsx": {
    "id": "d6kyt4",
    "url": "https://codesandbox.io/s/d6kyt4"
  },
  "ColumnPinningDemo.tsx": {
    "id": "6pd3pv",
    "url": "https://codesandbox.io/s/6pd3pv"
  },
  "ColumnReorderingDemo.tsx": {
    "id": "mxdwdx",
    "url": "https://codesandbox.io/s/mxdwdx"
  },
  "ColumnResizingDemo.tsx": {
    "id": "xg5ntp",
    "url": "https://codesandbox.io/s/xg5ntp"
  },
  "ColumnSelectionDemo.tsx": {
    "id": "ddzryt",
    "url": "https://codesandbox.io/s/ddzryt"
  },
  "ColumnSortingDemo.tsx": {
    "id": "x8rf2f",
    "url": "https://codesandbox.io/s/x8rf2f"
  },
  "ColumnVisibilityDemo.tsx": {
    "id": "w2cqhs",
    "url": "https://codesandbox.io/s/w2cqhs"
  },
  "ColumnWidthDemo.tsx": {
    "id": "pdnmn3",
    "url": "https://codesandbox.io/s/pdnmn3"
  },
  "CustomIconsDemo.tsx": {
    "id": "w5xxxk",
    "url": "https://codesandbox.io/s/w5xxxk"
  },
  "DynamicRowLoadingDemo.tsx": {
    "id": "7xvgmq",
    "url": "https://codesandbox.io/s/7xvgmq"
  },
  "OrganizationHierarchyExample.tsx": {
    "id": "placeholder",
    "url": "https://codesandbox.io/s/placeholder"
  },
  "ExternalFilterDemo.tsx": {
    "id": "rqtggs",
    "url": "https://codesandbox.io/s/rqtggs"
  },
  "ExternalSortDemo.tsx": {
    "id": "99j4jv",
    "url": "https://codesandbox.io/s/99j4jv"
  },
  "FooterRendererDemo.tsx": {
    "id": "xzpdkj",
    "url": "https://codesandbox.io/s/xzpdkj"
  },
  "HeaderRendererDemo.tsx": {
    "id": "3rkd95",
    "url": "https://codesandbox.io/s/3rkd95"
  },
  "InfiniteScrollDemo.tsx": {
    "id": "lzkwcr",
    "url": "https://codesandbox.io/s/lzkwcr"
  },
  "LiveUpdateDemo.tsx": {
    "id": "drctyn",
    "url": "https://codesandbox.io/s/drctyn"
  },
  "LoadingStateDemo.tsx": {
    "id": "99rw4w",
    "url": "https://codesandbox.io/s/99rw4w"
  },
  "NestedHeadersDemo.tsx": {
    "id": "t4pf2h",
    "url": "https://codesandbox.io/s/t4pf2h"
  },
  "PaginationDemo.tsx": {
    "id": "d79f4m",
    "url": "https://codesandbox.io/s/d79f4m"
  },
  "QuickStartDemo.tsx": {
    "id": "cghxzf",
    "url": "https://codesandbox.io/s/cghxzf"
  },
  "RowGroupingDemo.tsx": {
    "id": "ppmxhn",
    "url": "https://codesandbox.io/s/ppmxhn"
  },
  "RowHeightDemo.tsx": {
    "id": "82n6hl",
    "url": "https://codesandbox.io/s/82n6hl"
  },
  "RowSelectionDemo.tsx": {
    "id": "2mp75p",
    "url": "https://codesandbox.io/s/2mp75p"
  },
  "SingleRowChildrenDemo.tsx": {
    "id": "fy5tsy",
    "url": "https://codesandbox.io/s/fy5tsy"
  },
  "ThemesDemo.tsx": {
    "id": "ny5nym",
    "url": "https://codesandbox.io/s/ny5nym"
  },
  "TooltipDemo.tsx": {
    "id": "plhms6",
    "url": "https://codesandbox.io/s/plhms6"
  },
  "src/CustomThemeDemo.tsx": {
    "id": "t4qy2x",
    "url": "https://codesandbox.io/s/t4qy2x"
  },
  "examples/billing/BillingExample.tsx": {
    "id": "g65c2y",
    "url": "https://codesandbox.io/s/g65c2y"
  },
  "examples/crm/CRMExample.tsx": {
    "id": "2wrwpk",
    "url": "https://codesandbox.io/s/2wrwpk"
  },
  "examples/hr/HRExample.tsx": {
    "id": "68l7mf",
    "url": "https://codesandbox.io/s/68l7mf"
  },
  "examples/infrastructure/InfrastructureExample.tsx": {
    "id": "7rkqzd",
    "url": "https://codesandbox.io/s/7rkqzd"
  },
  "examples/manufacturing/ManufacturingExample.tsx": {
    "id": "vgsd86",
    "url": "https://codesandbox.io/s/vgsd86"
  },
  "examples/music/MusicExample.tsx": {
    "id": "rtvdjs",
    "url": "https://codesandbox.io/s/rtvdjs"
  },
  "examples/sales/SalesExample.tsx": {
    "id": "f9fwrj",
    "url": "https://codesandbox.io/s/f9fwrj"
  },
  "ValueFormatterDemo.tsx": {
    "id": "7qx2cj",
    "url": "https://codesandbox.io/s/7qx2cj"
  },
  "examples/organization-hierarchy/OrganizationHierarchyExample.tsx": {
    "id": "cfy9kv",
    "url": "https://codesandbox.io/s/cfy9kv"
  },
  "EmptyStateDemo.tsx": {
    "id": "g4537j",
    "url": "https://codesandbox.io/s/g4537j"
  },
  "TableHeightDemo.tsx": {
    "id": "3m2r4j",
    "url": "https://codesandbox.io/s/3m2r4j"
  }
}